biblionix/__init__.py
biblionix-2026.0.dist-info/WHEEL
biblionix-2026.0.dist-info/METADATA
biblionix-2026.0.dist-info/RECORD
