Metadata-Version: 2.4
Name: biblionix
Version: 2026.0
Summary: Python client library to interface with Biblionix library systems
Author: William Jackson
Author-email: William Jackson <william@subtlecoolness.com>
License-Expression: MIT
Classifier: Programming Language :: Python :: 3
Classifier: Operating System :: OS Independent
Requires-Dist: httpx>=0.28.1
Requires-Python: >=3.10
Project-URL: Changes, https://github.com/williamjacksn/python-biblionix/releases
Project-URL: Homepage, https://github.com/williamjacksn/python-biblionix
Project-URL: Issues, https://github.com/williamjacksn/python-biblionix/issues
